aionewsapi/__init__.py
aionewsapi/articles.py
aionewsapi/client.py
aionewsapi/exceptions.py
aionewsapi/http_client.py
aionewsapi/schema.py
aionewsapi-1.1.2.dist-info/METADATA
aionewsapi-1.1.2.dist-info/RECORD
aionewsapi-1.1.2.dist-info/WHEEL
aionewsapi-1.1.2.dist-info/top_level.txt
