Metadata-Version: 2.1
Name: aionewsapi
Version: 1.1.2
Summary: Asyncio client for interacting with newsapi.org
Home-page: https://github.com/mfdeux/aionewsapi
Author: Marc Ford
License: MIT
Platform: UNKNOWN
Classifier: License :: OSI Approved :: MIT License
Classifier: Programming Language :: Python :: 3.6
Classifier: Programming Language :: Python :: 3.7
Classifier: Operating System :: OS Independent
Requires-Dist: aiohttp
Requires-Dist: marshmallow
Requires-Dist: python-dateutil
